cursor_resumer/__init__.py
cursor_resumer/main.py
cursor_resumer-1.0.0.dist-info/licenses/LICENSE
cursor_resumer-1.0.0.dist-info/METADATA
cursor_resumer-1.0.0.dist-info/WHEEL
cursor_resumer-1.0.0.dist-info/entry_points.txt
cursor_resumer-1.0.0.dist-info/top_level.txt
cursor_resumer-1.0.0.dist-info/RECORD
