Metadata-Version: 2.4
Name: cursor-resumer
Version: 1.0.0
Summary: Automatically clicks resume button when Cursor AI hits 25 tool call limit
Home-page: https://github.com/khaterdev/cursor-resumer
Author: khaterdev
Author-email: khaterdev <mostafa@khater.dev>
License: MIT
Project-URL: Homepage, https://github.com/khaterdev/cursor-resumer
Project-URL: Bug Reports, https://github.com/khaterdev/cursor-resumer/issues
Project-URL: Source Code, https://github.com/khaterdev/cursor-resumer
Keywords: cursor,ai,automation,resume,tool-limit
Classifier: Development Status :: 4 - Beta
Classifier: Intended Audience :: Developers
Classifier: Topic :: Software Development :: Libraries :: Python Modules
Classifier: License :: OSI Approved :: MIT License
Classifier: Programming Language :: Python :: 3
Classifier: Programming Language :: Python :: 3.7
Classifier: Programming Language :: Python :: 3.8
Classifier: Programming Language :: Python :: 3.9
Classifier: Programming Language :: Python :: 3.10
Classifier: Programming Language :: Python :: 3.11
Classifier: Programming Language :: Python :: 3.12
Classifier: Operating System :: MacOS :: MacOS X
Requires-Python: >=3.7
License-File: LICENSE
Requires-Dist: pyautogui>=0.9.54
Requires-Dist: opencv-python>=4.9.0.80
Requires-Dist: Pillow>=10.2.0
Requires-Dist: pytesseract>=0.3.10
Requires-Dist: numpy>=1.26.4
Dynamic: author
Dynamic: home-page
Dynamic: license-file
Dynamic: requires-python
